saleor_gql_loader/__init__.py
saleor_gql_loader/data_loader.py
saleor_gql_loader/utils.py
saleor_gql_loader-0.0.5.dist-info/LICENSE.txt
saleor_gql_loader-0.0.5.dist-info/METADATA
saleor_gql_loader-0.0.5.dist-info/WHEEL
saleor_gql_loader-0.0.5.dist-info/top_level.txt
saleor_gql_loader-0.0.5.dist-info/RECORD
